{
  "version": "7",
  "dialect": "postgresql",
  "entries": [
    {
      "idx": 0,
      "version": "7",
      "when": 1755093482425,
      "tag": "0000_handy_madame_web",
      "breakpoints": true
    },
    {
      "idx": 1,
      "version": "7",
      "when": 1755105527191,
      "tag": "0001_volatile_may_parker",
      "breakpoints": true
    },
    {
      "idx": 2,
      "version": "7",
      "when": 1755253879156,
      "tag": "0002_bumpy_sugar_man",
      "breakpoints": true
    }
  ]
}